s3uploader/__init__.py
s3uploader/main.py
s3uploader/uploader.py
s3uploader-0.1.dist-info/DESCRIPTION.rst
s3uploader-0.1.dist-info/METADATA
s3uploader-0.1.dist-info/RECORD
s3uploader-0.1.dist-info/WHEEL
s3uploader-0.1.dist-info/entry_points.txt
s3uploader-0.1.dist-info/metadata.json
s3uploader-0.1.dist-info/top_level.txt
