Metadata-Version: 2.0
Name: s3uploader
Version: 0.1
Summary: Upload files to an Amazon S3 bucket
Home-page: https://bitbucket.org/michaelanckaert/s3uploader/
Author: Michael Anckaert
Author-email: michael.anckaert@sinax.be
License: MIT
Keywords: aws s3 uploader amazon
Platform: UNKNOWN
Classifier: Development Status :: 3 - Alpha
Classifier: Environment :: Console
Classifier: Intended Audience :: End Users/Desktop
Classifier: Intended Audience :: Developers
Classifier: Intended Audience :: System Administrators
Classifier: License :: OSI Approved :: MIT License
Classifier: Operating System :: MacOS :: MacOS X
Classifier: Operating System :: Microsoft :: Windows
Classifier: Operating System :: POSIX
Classifier: Programming Language :: Python :: 3.5
Classifier: Topic :: Utilities
Requires-Dist: boto3
